{
  "$schema": "https://developer.microsoft.com/json-schemas/rush/v5/rush.schema.json",
  "rushVersion": "5.13.0",
  "pnpmVersion": "3.8.1",
  "pnpmOptions": {
    // "strictPeerDependencies": true,
  },

  "nodeSupportedVersionRange": ">=10.13.0 <11.0.0",
  "projectFolderMaxDepth": 3,

  "gitPolicy": {

  },

  "repository": {
    "url": "https://github.com/fponticelli/mooo2"
  },

  "eventHooks": {
    "preRushInstall": [
      // "common/scripts/pre-rush-install.js"
    ],

    "postRushInstall": [],

    "preRushBuild": [],

    "postRushBuild": []
  },

  "variants": [
  ],

  "projects": [
    {
      "packageName": "mood",
      "projectFolder": "."
    }, {
      "packageName": "@mood/core",
      "projectFolder": "./core"
    }, {
      "packageName": "@mood/store",
      "projectFolder": "./store"
    }, {
      "packageName": "@mood/dom",
      "projectFolder": "./dom"
    }, {
      "packageName": "@mood/demo.todomvc",
      "projectFolder": "./demo/todomvc"
    }, {
      "packageName": "@mood/demo.readme",
      "projectFolder": "./demo/readme"
    }, {
      "packageName": "@mood/demo.benchmark",
      "projectFolder": "./demo/benchmark"
    }
  ]
}
