{
  "tempo-store": {
    "Introduction": [
      "index",
      "globals"
    ],
    "External Modules": [
      "modules/_emitter_",
      "classes/_emitter_.emitter",
      "modules/_index_",
      "modules/_listener_",
      "modules/_observable_",
      "interfaces/_observable_.observable",
      "modules/_property_",
      "classes/_property_.property",
      "modules/_reducer_",
      "modules/_store_",
      "classes/_store_.store"
    ],
    "Classes": [
      "classes/_emitter_.emitter",
      "classes/_property_.property",
      "classes/_store_.store"
    ],
    "Interfaces": [
      "interfaces/_observable_.observable"
    ]
  }
}